[
  {
    "id": "N_RSS_66702",
    "type": "official",
    "date": "2026-07-01",
    "likes": 117,
    "title": {
      "en": "Genuine superstar Kane produces his biggest England moment",
      "zh-CN": "真正的超级巨星凯恩创造了他最大的英格兰时刻"
    },
    "summary": {
      "en": "Harry Kane's England career is filled with great moments - his World Cup rescue act against DR Congo in Atlanta is his greatest, says chief football writer Phil McNulty.",
      "zh-CN": "首席足球作家菲尔·麦克纳尔蒂（ Phil McNulty ）表示，哈里·凯恩（ Harry Kane ）在英格兰的职业生涯充满了美好的时刻--他在亚特兰大对阵刚果民主共和国的世界杯救"
    },
    "source": "BBC Sport",
    "url": "https://www.bbc.co.uk/sport/football/articles/cvgd12vj79qo?at_medium=RSS&at_campaign=rss"
  },
  {
    "id": "N_RSS_99597",
    "type": "official",
    "date": "2026-07-01",
    "likes": 128,
    "title": {
      "en": "All the angles of Kane's brilliant winner",
      "zh-CN": "凯恩的辉煌胜利者的所有角度"
    },
    "summary": {
      "en": "All the angles of Harry Kane's winning goal against DR Congo for England in their round of 32 game in Atlanta.",
      "zh-CN": "哈里·凯恩在亚特兰大32轮比赛中为英格兰队对阵刚果民主共和国的胜利进球的所有角度。"
    },
    "source": "BBC Sport",
    "url": "https://www.bbc.co.uk/sport/football/videos/cgev83898nzo?at_medium=RSS&at_campaign=rss"
  },
  {
    "id": "N_RSS_34379",
    "type": "official",
    "date": "2026-07-01",
    "likes": 107,
    "title": {
      "en": "Four die in Mexico City World Cup celebrations",
      "zh-CN": "墨西哥城世界杯庆祝活动中有四人死亡"
    },
    "summary": {
      "en": "More than one million people took to the streets of Mexico's capital on Tuesday to mark the country's win over Ecuador.",
      "zh-CN": "周二，超过一百万人走上墨西哥首都的街头，纪念该国战胜厄瓜多尔。"
    },
    "source": "BBC Sport",
    "url": "https://www.bbc.co.uk/news/articles/cx2xjwj8p39o?at_medium=RSS&at_campaign=rss"
  },
  {
    "id": "N_RSS_13125",
    "type": "official",
    "date": "2026-07-01",
    "likes": 174,
    "title": {
      "en": "Concern over rise in online racist abuse at World Cup",
      "zh-CN": "对世界杯期间在线种族主义虐待上升的担忧"
    },
    "summary": {
      "en": "The Word Cup has suffered a 'significant increase' in the most serious examples of racist abuse online, Fifa's social media protection service (SMPS) has found.",
      "zh-CN": "国际足联的社交媒体保护服务（ SMPS ）发现， Word Cup在网上最严重的种族主义虐待事件中“大幅增加”。"
    },
    "source": "BBC Sport",
    "url": "https://www.bbc.co.uk/sport/football/articles/c1dy61921kko?at_medium=RSS&at_campaign=rss"
  },
  {
    "id": "N_RSS_68934",
    "type": "official",
    "date": "2026-07-01",
    "likes": 94,
    "title": {
      "en": "United, free and brilliant - can anyone stop France masterclass?",
      "zh-CN": "团结、自由、才华横溢--有人能阻止法国大师班吗？"
    },
    "summary": {
      "en": "France boss Didier Deschamps urges caution despite watching his side dismantle Sweden to leave Les Bleus fans dreaming of winning the World Cup.",
      "zh-CN": "法国主教练迪迪埃·德尚（ Didier Deschamps ）敦促谨慎行事，尽管他看着自己的球队拆除瑞典队，让蓝军球迷梦想着赢得世界杯。"
    },
    "source": "BBC Sport",
    "url": "https://www.bbc.co.uk/sport/football/articles/cp8r1zdj9k5o?at_medium=RSS&at_campaign=rss"
  },
  {
    "id": "N_RSS_84967",
    "type": "official",
    "date": "2026-07-01",
    "likes": 153,
    "title": {
      "en": "'Wonderful finish' - Cipenga gives DR Congo shock lead against England",
      "zh-CN": "“精彩的结局” - Cipenga让刚果民主共和国在对阵英格兰的比赛中领先"
    },
    "summary": {
      "en": "Brian Cipenga gives DR Congo an early lead against England during their World Cup last-32 match in Atlanta.",
      "zh-CN": "布莱恩·西彭加（ Brian Cipenga ）在亚特兰大的世界杯最后32场比赛中让刚果民主共和国队早早领先英格兰队"
    },
    "source": "BBC Sport",
    "url": "https://www.bbc.co.uk/sport/football/videos/cjdg9vp3m1po?at_medium=RSS&at_campaign=rss"
  },
  {
    "id": "N_RSS_34557",
    "type": "official",
    "date": "2026-07-01",
    "likes": 124,
    "title": {
      "en": "Beccacece reign as Ecuador manager  over after exit",
      "zh-CN": "Beccacece在退出后担任厄瓜多尔经理"
    },
    "summary": {
      "en": "Ecuador manager Sebastian Beccacece says he is leaving his role following his side's World Cup exit against Mexico.",
      "zh-CN": "厄瓜多尔主教练塞巴斯蒂安·贝卡塞斯（ Sebastian Beccacece ）表示，在他的球队对阵墨西哥的世界杯退出后，他将"
    },
    "source": "BBC Sport",
    "url": "https://www.bbc.co.uk/sport/football/articles/c932jj0d25no?at_medium=RSS&at_campaign=rss"
  },
  {
    "id": "N_RSS_88871",
    "type": "official",
    "date": "2026-07-01",
    "likes": 194,
    "title": {
      "en": "Villa sign Denmark striker Vangsgaard",
      "zh-CN": "丹麦前锋Vangsgaard的别墅标志"
    },
    "summary": {
      "en": "Amalie Vangsgaard says she is \"very excited for this new adventure\" after joining Aston Villa from Juventus.",
      "zh-CN": "Amalie Vangsgaard表示，从尤文图斯加入阿斯顿维拉后，她“对这次新的冒险感到非常兴奋”。"
    },
    "source": "BBC Sport",
    "url": "https://www.bbc.co.uk/sport/football/articles/c862yegveq2o?at_medium=RSS&at_campaign=rss"
  },
  {
    "id": "N_RSS_8101",
    "type": "official",
    "date": "2026-07-01",
    "likes": 159,
    "title": {
      "en": "Who has been eliminated from the World Cup?",
      "zh-CN": "谁被淘汰出世界杯？"
    },
    "summary": {
      "en": "BBC Sport's Ask Me Anything team lists the full set of nations who have been eliminated from the 2026 World Cup so far",
      "zh-CN": "BBC Sport的Ask Me Anything团队列出了迄今为止被2026年世界杯淘汰的全部国家"
    },
    "source": "BBC Sport",
    "url": "https://www.bbc.co.uk/sport/football/articles/c74y970len4o?at_medium=RSS&at_campaign=rss"
  },
  {
    "id": "N_RSS_73469",
    "type": "official",
    "date": "2026-07-01",
    "likes": 90,
    "title": {
      "en": "Harry Kane: Special, saviour, England's greatest and Ballon D'Or contender",
      "zh-CN": "哈里·凯恩：特别、救世主、英格兰最伟大的金球奖竞争者"
    },
    "summary": {
      "en": "Yes, England have issues. They put you through the mill, they're struggling for a right-back. But one problem they don't have is having a world-class matchwinner in their team.",
      "zh-CN": "是的，英格兰有问题。他们让你穿过磨坊，他们正在努力争取右后卫。但他们没有一个问题，那就是在他们的团队中拥有一个世界级的匹配者。"
    },
    "source": "Sky Sports",
    "url": "https://www.skysports.com/football/news/11095/13559651/harry-kane-england-captain-shows-why-he-is-greatest-every-striker-and-ballon-dor-contender-after-two-goal-heroics-against-dr-congo"
  },
  {
    "id": "N_RSS_59672",
    "type": "official",
    "date": "2026-07-01",
    "likes": 182,
    "title": {
      "en": "Ismaila Sarr smashes in Senegal second vs Belgium LIVE!",
      "zh-CN": "伊斯梅拉·萨尔（ Ismaila Sarr ）在塞内加尔与比利时的比赛中取得第二名！"
    },
    "summary": {
      "en": ""
    },
    "source": "Sky Sports",
    "url": "https://www.skysports.com/football/belgium-vs-senegal/live/549846"
  },
  {
    "id": "N_RSS_98890",
    "type": "official",
    "date": "2026-07-01",
    "likes": 112,
    "title": {
      "en": "Is Rice the solution to England's right-back problem?",
      "zh-CN": "赖斯是英格兰右后卫问题的解决方案吗？"
    },
    "summary": {
      "en": "England are through to the last 16 of the World Cup. Nobody will remember that they flirted with disaster in the round of 32 if they go on and lift the trophy. But Thomas Tuchel will be aware of the...",
      "zh-CN": "英格兰队进入了世界杯的最后16场比赛。如果他们继续举起奖杯，没有人会记得他们在32轮比赛中遇到了灾难。但托马斯·图切尔（ Thomas Tuchel ）会意识到……"
    },
    "source": "Sky Sports",
    "url": "https://www.skysports.com/football/news/11095/13559645/declan-rice-could-be-best-solution-to-thomas-tuchels-right-back-issue-after-cameo-in-england-win-over-dr-congo"
  },
  {
    "id": "N_RSS_47328",
    "type": "official",
    "date": "2026-07-01",
    "likes": 300,
    "title": {
      "en": "World Cup latest: Nagelsmann's future in doubt with Klopp 'dream candidate'",
      "zh-CN": "世界杯最新消息：纳格尔斯曼的未来受到克洛普“梦想候选人”的质疑"
    },
    "summary": {
      "en": ""
    },
    "source": "Sky Sports",
    "url": "https://www.skysports.com/football/live-blog/11095/13509050/world-cup-2026-news-and-live-updates-usa-canada-and-mexico-latest-including-trump-tickets-and-fans"
  },
  {
    "id": "N_RSS_21595",
    "type": "official",
    "date": "2026-07-01",
    "likes": 298,
    "title": {
      "en": "Belgium v Senegal: World Cup last 32 – live",
      "zh-CN": "比利时v塞内加尔：世界杯最后32场–直播"
    },
    "summary": {
      "en": "⚽️ Kick-off time: 4pm EDT/9pm BST/6am AEST⚽️ Player guide | Bracketology | Golden Boot“Well, I’m going to come right out and say that I’ve never heard of Sparklehorse,” says Charles Antaki. “There;...",
      "zh-CN": "⚽️ 开⚽️球时间：美国东部夏令时下午4点/英国夏令时晚上9点/美国东部夏令时上午6点球员指南| Bracketology | Golden Boot “好吧，我要出来说我从来没有听说过Sparklehorse ，” Charles Antaki说。“那儿……"
    },
    "source": "The Guardian",
    "url": "https://www.theguardian.com/football/live/2026/jul/01/belgium-v-senegal-world-cup-last-32-live"
  },
  {
    "id": "N_RSS_83426",
    "type": "official",
    "date": "2026-07-01",
    "likes": 210,
    "title": {
      "en": "German police raid national football HQ over Euro 2024 corruption allegations",
      "zh-CN": "德国警方突击搜查了2024年欧洲杯腐败指控的国家足球总部"
    },
    "summary": {
      "en": "Operation concerns ‘unauthorised favours’ in host citiesBribery involving tickets is suspected, Bild reportsPolice in Germany have raided the national football federation headquarters and other sites...",
      "zh-CN": "主办城市的运营担忧“未经授权的恩惠”涉嫌涉及门票的贿赂、《图片报》报道德国警方突袭了国家足球联合会总部和其他场所……"
    },
    "source": "The Guardian",
    "url": "https://www.theguardian.com/football/2026/jul/01/german-police-raid-national-football-hq-over-euro-2024-corruption-allegations"
  },
  {
    "id": "N_RSS_77724",
    "type": "official",
    "date": "2026-07-01",
    "likes": 205,
    "title": {
      "en": "‘An artist who captures hearts’: France is falling in love with Michael Olise"
    },
    "summary": {
      "en": "Bayern Munich forward is yet to score at this World Cup, but his style and assists are bringing joy back homeBy Get French Football News“Go on, feel free to find the issues,” Didier Deschamps..."
    },
    "source": "The Guardian",
    "url": "https://www.theguardian.com/football/2026/jul/01/michael-olise-artist-hearts-france-love-world-cup-bayern-munich"
  },
  {
    "id": "N_RSS_78894",
    "type": "official",
    "date": "2026-07-01",
    "likes": 180,
    "title": {
      "en": "Fabián Ruiz: ‘It’s not important who plays, it’s important we support each other’ | Sid Lowe"
    },
    "summary": {
      "en": "On the eve of their last-32 game with Austria, Spain’s unassuming midfielder explains their team spirit and about finding his rhythm after injuryAt the Embassy Suites on Broad Street, downtown..."
    },
    "source": "The Guardian",
    "url": "https://www.theguardian.com/football/2026/jul/01/fabian-ruiz-spain-austria-world-cup-2026-round-32"
  },
  {
    "id": "N_RSS_20305",
    "type": "official",
    "date": "2026-07-01",
    "likes": 183,
    "title": {
      "en": "England 2-1 DR Congo: World Cup last 32 player ratings"
    },
    "summary": {
      "en": "Anthony Gordon showed why he is joining Barcelona but a brilliant Lionel Mpasi in goal could not stop Harry KaneJordan Pickford Got a hand to Cipenga’s strike but could have done better. Will be..."
    },
    "source": "The Guardian",
    "url": "https://www.theguardian.com/football/2026/jul/01/england-2-1-dr-congo-world-cup-last-32-player-ratings"
  },
  {
    "id": "N_RSS_21069",
    "type": "official",
    "date": "2026-07-01",
    "likes": 281,
    "title": {
      "en": "Four people die in mass fan celebrations in Mexico City after World Cup victory"
    },
    "summary": {
      "en": "Three of the victims died from suffocationMore than a million people gathered in Mexico CityFour people died, three ⁠from suffocation, as thousands of fans crowded Mexico City streets during World..."
    },
    "source": "The Guardian",
    "url": "https://www.theguardian.com/football/2026/jul/01/deaths-mexico-world-cup-fan-celebrations"
  },
  {
    "id": "N_RSS_12452",
    "type": "official",
    "date": "2026-07-01",
    "likes": 249,
    "title": {
      "en": "In ceding the reins to Mbappé, Olise and Dembélé, France look as under control as ever"
    },
    "summary": {
      "en": "Didier Deschamps used to manage with an iron fist. This time, he’s letting his stars run the show – to Les Bleus’ benefitWhen a cat has cornered a mouse and appears to be toying with its prey, it..."
    },
    "source": "The Guardian",
    "url": "https://www.theguardian.com/football/2026/jul/01/france-world-cup-mbappe-olise-dembele"
  },
  {
    "id": "N_RSS_37288",
    "type": "official",
    "date": "2026-07-01",
    "likes": 84,
    "title": {
      "en": "‘It’s like being close to home’: World Cup vibes immaculate in richly diverse New York"
    },
    "summary": {
      "en": "Fans of all stripes pack the bars to sing, cheer and commiserate in city where more than 3m people were born outside USAlmost 200,000 Ecuadorians and Ecuadorian Americans live in New York City, and..."
    },
    "source": "The Guardian",
    "url": "https://www.theguardian.com/football/2026/jul/01/world-cup-new-york"
  },
  {
    "id": "N_RSS_67979",
    "type": "official",
    "date": "2026-07-01",
    "likes": 201,
    "title": {
      "en": "England avert disaster against DR Congo but they must be better in Mexico City | Jacob Steinberg"
    },
    "summary": {
      "en": "It was an almost Iceland in Atlanta but Thomas Tuchel will have to get it right from the start in the cauldron of AztecaIt was looking bleak out there. Ten years on, it was looking like Iceland all..."
    },
    "source": "The Guardian",
    "url": "https://www.theguardian.com/football/2026/jul/01/england-avert-disaster-against-dr-congo-but-they-must-be-better-in-mexico-city"
  },
  {
    "id": "N_RSS_32924",
    "type": "official",
    "date": "2026-07-01",
    "likes": 127,
    "title": {
      "en": "‘Would you say it to someone’s face?’ Ellen White on going from player to pundit"
    },
    "summary": {
      "en": "In this week’s newsletter we speak to the Lionesses’ record scorer, who has been inducted to the hall of fame at the National Football MuseumFor a generation of England fans she was the talismanic..."
    },
    "source": "The Guardian",
    "url": "https://www.theguardian.com/football/2026/jul/01/ellen-white-england-lionesses-player-to-pundit"
  },
  {
    "id": "N_RSS_57338",
    "type": "official",
    "date": "2026-07-01",
    "likes": 59,
    "title": {
      "en": "Mexico end World Cup knockout drought with last-32 win over Ecuador in Azteca cauldron"
    },
    "summary": {
      "en": "They were held up by an electric storm but, after the skies had cleared, Mexico kept the lightning bolts coming. This was a climactic night that utterly engulfed the senses and its ramifications will..."
    },
    "source": "The Guardian",
    "url": "https://www.theguardian.com/football/2026/jul/01/mexico-ecuador-world-cup-2026-last-32-match-report"
  },
  {
    "id": "N_RSS_83622",
    "type": "official",
    "date": "2026-07-01",
    "likes": 280,
    "title": {
      "en": "Kylian Mbappé at the double as France swat aside Sweden in World Cup masterclass"
    },
    "summary": {
      "en": "When people form memories of the World Cup, it’s matches like this that do it. France once again won comprehensively, and against decent opposition, but the quality of their attacking play, and the..."
    },
    "source": "The Guardian",
    "url": "https://www.theguardian.com/football/2026/jul/01/france-sweden-world-cup-2026-last-32-match-report"
  },
  {
    "id": "N_RSS_62416",
    "type": "official",
    "date": "2026-07-01",
    "likes": 216,
    "title": {
      "en": "Haaland is inevitable for Norway but are France unstoppable? | World Cup Daily"
    },
    "summary": {
      "en": "Max Rushden is joined by Barry Glendenning, Archie Rhind-Tutt and Dan Bardell as France breeze past Sweden and Haaland wins it late for Norway Continue reading..."
    },
    "source": "The Guardian",
    "url": "https://www.theguardian.com/football/video/2026/jul/01/haaland-is-inevitable-for-norway-but-are-france-unstoppable-world-cup-daily"
  },
  {
    "id": "N_RSS_66393",
    "type": "official",
    "date": "2026-07-01",
    "likes": 157,
    "title": {
      "en": "Who has scored the most goals at a World Cup without winning the Golden Boot?"
    },
    "summary": {
      "en": "Plus: World Cup teams stuck on nul points and teams who broke their duck with a drubbingMail us with your all of your questions and answers“Who has scored the most goals at a World Cup finals without..."
    },
    "source": "The Guardian",
    "url": "https://www.theguardian.com/football/2026/jul/01/knowledge-world-cup-most-goals-without-golden-boot"
  },
  {
    "id": "N_RSS_69848",
    "type": "official",
    "date": "2026-07-01",
    "likes": 223,
    "title": {
      "en": "Football Daily | France’s fab front four make them incomparable World Cup favourites"
    },
    "summary": {
      "en": "Sign up now! Sign up now! Sign up now? Sign up now!We can all agree the Geopolitics World Cup has gone on far too long, so Football Daily is pleased to announce it is over. It monopolises everyone’s..."
    },
    "source": "The Guardian",
    "url": "https://www.theguardian.com/football/2026/jul/01/frances-fab-front-four-make-them-incomparable-world-cup-favourites"
  },
  {
    "id": "N_RSS_94015",
    "type": "official",
    "date": "2026-06-30",
    "likes": 294,
    "title": {
      "en": "Mbappe scores twice as France dominate Sweden"
    },
    "summary": {
      "en": "Kylian Mbappe becomes the all-time leading goalscorer in World Cup knockout matches with after scoring twice as France crusie past Sweden 3-0 to set up a last-16 tie with Paraguay."
    },
    "source": "BBC Sport",
    "url": "https://www.bbc.co.uk/sport/football/videos/c6216q7d62ro?at_medium=RSS&at_campaign=rss"
  },
  {
    "id": "N_RSS_54487",
    "type": "official",
    "date": "2026-06-30",
    "likes": 118,
    "title": {
      "en": "The Paraguay hero who sold his kit when his son was born"
    },
    "summary": {
      "en": "Orlando Gill has become Paraguay's World Cup hero but was in football obscurity 18 months ago and had to sell his kit to support his family after the premature birth of his son."
    },
    "source": "BBC Sport",
    "url": "https://www.bbc.co.uk/sport/football/articles/c75yelwge25o?at_medium=RSS&at_campaign=rss"
  }
]