[
  {
    "id": "N_RSS_38390",
    "type": "official",
    "date": "2026-07-17",
    "likes": 207,
    "title": {
      "en": "Five reasons for England to be cheerful despite World Cup exit",
      "zh-CN": "尽管世界杯退出，英格兰仍然开朗的五个原因"
    },
    "summary": {
      "en": "Despite the heartbreak of a World Cup semi-final loss, there are plenty of reasons to be optimistic about England's footballing future.",
      "zh-CN": "尽管世界杯半决赛失利让人心碎，但有很多理由对英格兰足球的未来持乐观态度。"
    },
    "source": "BBC Sport",
    "url": "https://www.bbc.co.uk/sport/football/articles/clyxllv7lmpo?at_medium=RSS&at_campaign=rss"
  },
  {
    "id": "N_RSS_78655",
    "type": "official",
    "date": "2026-07-17",
    "likes": 158,
    "title": {
      "en": "'Chaos v calm' - Sutton's World Cup final and third-place predictions",
      "zh-CN": "“混沌v平静” -萨顿的世界杯决赛和第三名预测"
    },
    "summary": {
      "en": "BBC Sport's football expert Chris Sutton makes his prediction for Spain against Argentina in the World Cup final, and the bronze final between France and England.",
      "zh-CN": "英国广播公司体育台的足球专家克里斯·萨顿（ Chris Sutton ）在世界杯决赛中对西班牙对阿根廷的预测，以及法国和英格兰之间的铜牌决赛。"
    },
    "source": "BBC Sport",
    "url": "https://www.bbc.co.uk/sport/football/articles/c4g3zrgxkzdo?at_medium=RSS&at_campaign=rss"
  },
  {
    "id": "N_RSS_60229",
    "type": "official",
    "date": "2026-07-17",
    "likes": 243,
    "title": {
      "en": "Are Argentina being treated favourably at World Cup?",
      "zh-CN": "阿根廷在世界杯上是否得到了有利的待遇？"
    },
    "summary": {
      "en": "Egypt have alleged bias in favour of Argentina and favouritism towards their star player, Lionel Messi. Is this fair?",
      "zh-CN": "埃及声称偏袒阿根廷，偏袒他们的明星球员莱昂内尔·梅西。这公平吗？"
    },
    "source": "BBC Sport",
    "url": "https://www.bbc.co.uk/sport/football/articles/cx2wkwd7e6go?at_medium=RSS&at_campaign=rss"
  },
  {
    "id": "N_RSS_19593",
    "type": "official",
    "date": "2026-07-17",
    "likes": 119,
    "title": {
      "en": "Thousands of tickets still available for England v France",
      "zh-CN": "英格兰v法国仍有数千张门票"
    },
    "summary": {
      "en": "Around 7,000 tickets are still listed on Fifa's ticket sites for Saturday's World Cup bronze medal match between England and France.",
      "zh-CN": "大约7,000张门票仍在国际足联的门票网站上列出，用于周六英格兰和法国之间的世界杯铜牌比赛。"
    },
    "source": "BBC Sport",
    "url": "https://www.bbc.co.uk/sport/football/articles/c5yd5kv1e5ko?at_medium=RSS&at_campaign=rss"
  },
  {
    "id": "N_RSS_76403",
    "type": "official",
    "date": "2026-07-17",
    "likes": 175,
    "title": {
      "en": "How World Cup final could be pivotal in Ballon d'Or race",
      "zh-CN": "世界杯决赛如何在Ballon d 'Or比赛中发挥关键作用"
    },
    "summary": {
      "en": "With the Ballon d'Or race tighter than ever before, BBC Sport looks at how the World Cup final could determine the 2026 winner.",
      "zh-CN": "随着Ballon d 'Or比赛比以往任何时候都更加激烈， BBC Sport着眼于世界杯决赛如何确定2026年的冠军。"
    },
    "source": "BBC Sport",
    "url": "https://www.bbc.co.uk/sport/football/articles/c87ngl370p4o?at_medium=RSS&at_campaign=rss"
  },
  {
    "id": "N_RSS_79566",
    "type": "official",
    "date": "2026-07-17",
    "likes": 229,
    "title": {
      "en": "World Cup rings for winners as Trump attendance confirmed",
      "zh-CN": "随着特朗普的出席率得到确认，世界杯冠军响起"
    },
    "summary": {
      "en": "Donald Trump will present the trophy to the World Cup final winners on Sunday, and rings will be presented to the victorious side.",
      "zh-CN": "唐纳德·特朗普将于周日向世界杯决赛冠军颁发奖杯，并向胜利一方颁发戒指。"
    },
    "source": "BBC Sport",
    "url": "https://www.bbc.co.uk/sport/football/articles/cgmk7mnnyjeo?at_medium=RSS&at_campaign=rss"
  },
  {
    "id": "N_RSS_37553",
    "type": "official",
    "date": "2026-07-17",
    "likes": 234,
    "title": {
      "en": "Spain 2010 v Spain 2026: How do the two XIs compare?",
      "zh-CN": "西班牙2010 vs西班牙2026 ：两个XI如何比较？"
    },
    "summary": {
      "en": "How do Spain's 2010 World Cup winners compare to the current contingent who are looking to match their feat in the 2026 tournament? BBC Sport takes a look.",
      "zh-CN": "西班牙2010年世界杯冠军与目前希望在2026年锦标赛中与他们的壮举相匹配的队伍相比如何？英国广播公司体育台（ BBC Sport ）正在播放。"
    },
    "source": "BBC Sport",
    "url": "https://www.bbc.co.uk/sport/football/articles/c5yzy1rzxepo?at_medium=RSS&at_campaign=rss"
  },
  {
    "id": "N_RSS_10269",
    "type": "official",
    "date": "2026-07-17",
    "likes": 59,
    "title": {
      "en": "World Cup quiz: Can you name finalists since 1930?",
      "zh-CN": "世界杯测验：您可以说出1930年以来的入围名单吗？"
    },
    "summary": {
      "en": "As we approach Sunday's World Cup final, test your knowledge of the teams who have made it to this stage before.",
      "zh-CN": "当我们接近周日的世界杯决赛时，请测试您对之前进入这个阶段的球队的了解程度。"
    },
    "source": "BBC Sport",
    "url": "https://www.bbc.co.uk/sport/football/articles/cj4pw98d29eo?at_medium=RSS&at_campaign=rss"
  },
  {
    "id": "N_RSS_13758",
    "type": "official",
    "date": "2026-07-17",
    "likes": 225,
    "title": {
      "en": "Uefa will not use VAR for diving like at World Cup",
      "zh-CN": "欧足联不会像世界杯那样使用VAR进行跳水"
    },
    "summary": {
      "en": "Uefa has told its video assistant referees (VARs) they must not consider potential simulation as mistaken identity, as seen at the 2026 World Cup.",
      "zh-CN": "欧足联告诉其视频助理裁判（ VAR ） ，他们不得将潜在的模拟视为错误的身份，正如在2026年世界杯上看到的那样。"
    },
    "source": "BBC Sport",
    "url": "https://www.bbc.co.uk/sport/football/articles/c89nlvwx410o?at_medium=RSS&at_campaign=rss"
  },
  {
    "id": "N_RSS_86218",
    "type": "official",
    "date": "2026-07-17",
    "likes": 69,
    "title": {
      "en": "Nine World Cup stars who could move this summer",
      "zh-CN": "今年夏天可以搬家的九位世界杯明星"
    },
    "summary": {
      "en": "As the World Cup approaches its end, attentions are turning to the 2026-27 club season - and the players who could be on the move this summer.",
      "zh-CN": "随着世界杯即将结束，人们的注意力正在转向2026-27俱乐部赛季-以及今年夏天可能移动的球员。"
    },
    "source": "BBC Sport",
    "url": "https://www.bbc.co.uk/sport/football/articles/c87ng4xq9nwo?at_medium=RSS&at_campaign=rss"
  },
  {
    "id": "N_RSS_26520",
    "type": "official",
    "date": "2026-07-17",
    "likes": 239,
    "title": {
      "en": "The financial winners and losers from the World Cup",
      "zh-CN": "世界杯的财务赢家和输家"
    },
    "summary": {
      "en": "Big bucks are being made from the 2026 tournament off the field, but who is raking in the most, and who is losing out?",
      "zh-CN": "2026年的锦标赛在场外赚了很多钱，但谁赚得最多，谁输得最少？"
    },
    "source": "BBC Sport",
    "url": "https://www.bbc.co.uk/news/articles/cgrkek8lrzvo?at_medium=RSS&at_campaign=rss"
  },
  {
    "id": "N_RSS_20587",
    "type": "official",
    "date": "2026-07-17",
    "likes": 296,
    "title": {
      "en": "West Ham sign forward Gago and defender Cascarino",
      "zh-CN": "西汉姆签约前锋Gago和后卫Cascarino"
    },
    "summary": {
      "en": "West Ham sign Everton striker Kelly Gago and turn fellow France international Estelle Cascarino's loan move into a permanent deal.",
      "zh-CN": "西汉姆联队签下了埃弗顿前锋凯利·加戈（ Kelly Gago ） ，并将法国国脚埃斯特尔·卡斯卡里诺（ Estelle Cascarino ）的租借"
    },
    "source": "BBC Sport",
    "url": "https://www.bbc.co.uk/sport/football/articles/c5yzye502vko?at_medium=RSS&at_campaign=rss"
  },
  {
    "id": "N_RSS_33824",
    "type": "official",
    "date": "2026-07-17",
    "likes": 146,
    "title": {
      "en": "Listen: How does Gordon rate in goalkeeping greats? Plus League Cup preview",
      "zh-CN": "听： Gordon在守门员方面的表现如何？ Plus联赛杯预览"
    },
    "summary": {
      "en": "Craig Gordon retires, League Cup preview and who's going to win the World Cup?",
      "zh-CN": "克雷格·戈登（ Craig Gordon ）退役，联赛杯预赛，谁将赢得世界杯？"
    },
    "source": "BBC Sport",
    "url": "https://www.bbc.co.uk/sounds/play/p0nzbjxn?at_medium=RSS&at_campaign=rss"
  },
  {
    "id": "N_RSS_58677",
    "type": "official",
    "date": "2026-07-17",
    "likes": 255,
    "title": {
      "en": "Birmingham City sign Canada defender Levasseur",
      "zh-CN": "伯明翰市签约加拿大后卫Levasseur"
    },
    "summary": {
      "en": "WSL newcomers Birmingham City have signed Canada international Marie Levasseur.",
      "zh-CN": "WSL新人伯明翰市签下了加拿大国脚Marie Levasseur。"
    },
    "source": "BBC Sport",
    "url": "https://www.bbc.co.uk/sport/football/articles/cx2d5l4q8jpo?at_medium=RSS&at_campaign=rss"
  },
  {
    "id": "N_RSS_2272",
    "type": "official",
    "date": "2026-07-17",
    "likes": 95,
    "title": {
      "en": "Why Arsenal have made Rogers their top forward target this summer",
      "zh-CN": "为什么阿森纳将罗杰斯作为今年夏天的首选前锋"
    },
    "summary": {
      "en": "It takes something special to earn the trust of Unai Emery, force your way into Thomas Tuchel's England plans and attract the interest of Europe's elite. Morgan Rogers has done all three and that is...",
      "zh-CN": "这需要一些特别的东西来赢得Unai Emery的信任，强行进入Thomas Tuchel的英格兰计划，并吸引欧洲精英的兴趣。摩根·罗杰斯（ Morgan Rogers ）已经完成了这三项工作，那就是……"
    },
    "source": "Sky Sports",
    "url": "https://www.skysports.com/football/news/11095/13556620/morgan-rogers-transfer-news-why-arsenal-have-made-aston-villa-star-their-top-forward-target-this-summer"
  },
  {
    "id": "N_RSS_54493",
    "type": "official",
    "date": "2026-07-17",
    "likes": 288,
    "title": {
      "en": "The remarkable Messi and Lamine Yamal photos showing 'the beginning of two legends'"
    },
    "summary": {
      "en": "Lionel Messi and Lamine Yamal will play against each other for the first time when Argentina face Spain in Sunday's World Cup final."
    },
    "source": "Sky Sports",
    "url": "https://www.skysports.com/football/news/11095/13564364/world-cup-final-2026-the-remarkable-photos-of-lionel-messi-and-lamine-yamals-first-meeting-as-they-prepare-to-face-off"
  },
  {
    "id": "N_RSS_65238",
    "type": "official",
    "date": "2026-07-17",
    "likes": 192,
    "title": {
      "en": "More than 200 countries endorse Infantino for fourth Fifa term despite Balogun scandal"
    },
    "summary": {
      "en": "Only a handful of FAs have not declared their supportUefa has made its opposition clear on number of issuesGianni Infantino has the formal endorsement of more than 200 countries for re-election as..."
    },
    "source": "The Guardian",
    "url": "https://www.theguardian.com/football/2026/jul/17/gianni-infantino-fifa-reelection-more-than-200-countries-endorse-despite-balogun-scandal"
  },
  {
    "id": "N_RSS_15835",
    "type": "official",
    "date": "2026-07-17",
    "likes": 191,
    "title": {
      "en": "Unbeatables v untouchables? Spain’s run faces ultimate test in World Cup final"
    },
    "summary": {
      "en": "Spain’s streak started after a defeat in 2024 but Argentina are no slouches – they are on an unbeaten run of 14 matchesSpain look unstoppable. Their 2-0 victory against France meant they have not..."
    },
    "source": "The Guardian",
    "url": "https://www.theguardian.com/football/2026/jul/17/unbeatables-v-untouchables-spains-run-faces-ultimate-test-in-world-cup-final"
  },
  {
    "id": "N_RSS_89466",
    "type": "official",
    "date": "2026-07-17",
    "likes": 115,
    "title": {
      "en": "Football Daily | Donald Trump gives himself starting role in the bigliest occasion of all"
    },
    "summary": {
      "en": "Sign up now! Sign up now! Sign up now? Sign up now!Donald Trump has largely steered clear of the Geopolitics World Cup: he is yet to attend a game and appear on screen with his good pal “Jonny”..."
    },
    "source": "The Guardian",
    "url": "https://www.theguardian.com/football/2026/jul/17/donald-trump-world-cup-2026-final-football-daily-newsletter"
  },
  {
    "id": "N_RSS_69128",
    "type": "official",
    "date": "2026-07-17",
    "likes": 137,
    "title": {
      "en": "The big World Cup final quiz"
    },
    "summary": {
      "en": "Argentina and Spain will contest the 23rd World Cup final on Sunday. How much do you know about the previous 22?This is a quiz by Richard Foster, who presents the It Started With A Kick podcast and..."
    },
    "source": "The Guardian",
    "url": "https://www.theguardian.com/football/2026/jul/17/world-cup-final-quiz-argentina-spain"
  },
  {
    "id": "N_RSS_67186",
    "type": "official",
    "date": "2026-07-17",
    "likes": 275,
    "title": {
      "en": "World Cup final, the Tour de France and Open golf – follow with us"
    },
    "summary": {
      "en": "Here’s how to follow along with our coverage – the finest writing and up-to-the-minute reports Continue reading..."
    },
    "source": "The Guardian",
    "url": "https://www.theguardian.com/sport/2026/jul/17/world-cup-final-the-tour-de-france-and-open-golf-follow-with-us"
  },
  {
    "id": "N_RSS_55521",
    "type": "official",
    "date": "2026-07-16",
    "likes": 211,
    "title": {
      "en": "All 11 last-minute winners at the World Cup"
    },
    "summary": {
      "en": "Watch all 11 winning goals scored in stoppage time at the 2026 Fifa World Cup."
    },
    "source": "BBC Sport",
    "url": "https://www.bbc.co.uk/sport/football/videos/cp8xn9y46xdo?at_medium=RSS&at_campaign=rss"
  },
  {
    "id": "N_RSS_17852",
    "type": "official",
    "date": "2026-07-16",
    "likes": 270,
    "title": {
      "en": "Some England players disappointed by tactics as Tuchel questions team's DNA"
    },
    "summary": {
      "en": "BBC Sport understands that Thomas Tuchel's defensive tactics in the World Cup semi-final defeat to Argentina are being hotly debated by the England squad."
    },
    "source": "BBC Sport",
    "url": "https://www.bbc.co.uk/sport/football/articles/cqjxl90x27ro?at_medium=RSS&at_campaign=rss"
  },
  {
    "id": "N_RSS_79491",
    "type": "official",
    "date": "2026-07-16",
    "likes": 277,
    "title": {
      "en": "'A true miracle of destiny' - Messi and Lamine Yamal's incredible first meeting"
    },
    "summary": {
      "en": "BBC Sport explores a bond between two world-class footballers from different generations who appear bound by destiny"
    },
    "source": "BBC Sport",
    "url": "https://www.bbc.co.uk/sport/football/articles/c9w0j104rvgo?at_medium=RSS&at_campaign=rss"
  },
  {
    "id": "N_RSS_62555",
    "type": "official",
    "date": "2026-07-16",
    "likes": 96,
    "title": {
      "en": "Why you should care about World Cup third-place play-off"
    },
    "summary": {
      "en": "It might feel like the last thing anyone wants right now - but here is why, actually, you do want to watch the World Cup's third-place play-off."
    },
    "source": "BBC Sport",
    "url": "https://www.bbc.co.uk/sport/football/articles/cly5we2lgq4o?at_medium=RSS&at_campaign=rss"
  },
  {
    "id": "N_RSS_25904",
    "type": "official",
    "date": "2026-07-16",
    "likes": 158,
    "title": {
      "en": "60 years of hurt - England's World Cup wait in numbers"
    },
    "summary": {
      "en": "England’s wait for another World Cup triumph wait told through the football, people and moments that have shaped the world since 1966."
    },
    "source": "BBC Sport",
    "url": "https://www.bbc.co.uk/sport/football/articles/czrjgpy48pgo?at_medium=RSS&at_campaign=rss"
  },
  {
    "id": "N_RSS_27673",
    "type": "official",
    "date": "2026-07-16",
    "likes": 59,
    "title": {
      "en": "Record crowd as Kerr returns to Gotham FC"
    },
    "summary": {
      "en": "Former Chelsea forward Sam Kerr makes her second debut for Gotham FC in front of the largest ever crowd for a women's sporting event in New York City."
    },
    "source": "BBC Sport",
    "url": "https://www.bbc.co.uk/sport/football/articles/ckge5jkjz9eo?at_medium=RSS&at_campaign=rss"
  },
  {
    "id": "N_RSS_49811",
    "type": "official",
    "date": "2026-07-16",
    "likes": 213,
    "title": {
      "en": "Palace sign England Under-23 striker Lloyd-Smith"
    },
    "summary": {
      "en": "Crystal Palace sign last season's WSL2 top scorer Lexi Lloyd-Smith on a three-year deal."
    },
    "source": "BBC Sport",
    "url": "https://www.bbc.co.uk/sport/football/articles/cz64xe19dy8o?at_medium=RSS&at_campaign=rss"
  },
  {
    "id": "N_RSS_72854",
    "type": "official",
    "date": "2026-07-16",
    "likes": 176,
    "title": {
      "en": "Neville: I have a big problem with Tuchel's DNA comments"
    },
    "summary": {
      "en": "Gary Neville has hit back at Thomas Tuchel's suggestions that English football's 'DNA' was to blame for their World Cup semi-final defeat to Argentina."
    },
    "source": "Sky Sports",
    "url": "https://www.skysports.com/football/news/11095/13564414/england-1-2-argentina-gary-neville-takes-issue-with-thomas-tuchels-english-dna-claims-following-world-cup-elimination"
  },
  {
    "id": "N_RSS_54871",
    "type": "official",
    "date": "2026-07-16",
    "likes": 286,
    "title": {
      "en": "Tuchel blames English football's 'DNA' for World Cup exit"
    },
    "summary": {
      "en": "Thomas Tuchel says he is \"100 per cent\" committed to continuing his role as England boss into the next European Championships in two years, and he has hit back at critics who have questioned his..."
    },
    "source": "Sky Sports",
    "url": "https://www.skysports.com/football/news/11095/13564152/thomas-tuchel-england-boss-defends-tactics-against-argentina-and-blames-english-footballs-dna-for-world-cup-exit"
  }
]